qserver_connect/__init__.py
qserver_connect/constants.py
qserver_connect/data_types.py
qserver_connect/exceptions.py
qserver_connect/job.py
qserver_connect/job_connection.py
qserver_connect/jobs_pb2.py
qserver_connect/jobs_pb2.pyi
qserver_connect/jobs_pb2_grpc.py
qserver_connect/plugin.py
qserver_connect/url.py
qserver_connect/adapters/__init__.py
qserver_connect/adapters/adapter.py
qserver_connect/adapters/qiskit.py
qserver_connect-0.0.22.dist-info/licenses/LICENSE
qserver_connect-0.0.22.dist-info/METADATA
qserver_connect-0.0.22.dist-info/WHEEL
qserver_connect-0.0.22.dist-info/top_level.txt
qserver_connect-0.0.22.dist-info/RECORD
