Metadata-Version: 2.4
Name: qserver_connect
Version: 0.0.22
Summary: A library to interact with your qserver
Home-page: https://github.com/Dpbm/qserver-connect
Author: Dpbm
Author-email: dpbm136@gmail.com
License: MIT
Classifier: Programming Language :: Python
Classifier: Programming Language :: Python :: 3
Classifier: Programming Language :: Python :: 3.0
Classifier: Programming Language :: Python :: 3.12
Classifier: Topic :: Scientific/Engineering
Classifier: Topic :: Scientific/Engineering :: Quantum Computing
Classifier: Topic :: Software Development
Classifier: Topic :: Software Development :: Libraries
Classifier: Topic :: System
Classifier: Topic :: System :: Hardware
License-File: LICENSE
Requires-Dist: grpcio
Requires-Dist: grpcio-tools
Requires-Dist: requests
Requires-Dist: qiskit==1.3.2
Requires-Dist: qiskit_qasm3_import
Dynamic: author
Dynamic: author-email
Dynamic: classifier
Dynamic: description
Dynamic: description-content-type
Dynamic: home-page
Dynamic: license
Dynamic: license-file
Dynamic: requires-dist
Dynamic: summary
